zpool_monitor/__init__.py
zpool_monitor/apps.py
zpool_monitor/cliargs.py
zpool_monitor/monitor.py
zpool_monitor/systemzpool.py
zpool_monitor/textual/__init__.py
zpool_monitor/textual/dashboard.css
zpool_monitor/textual/dashboard.py
zpool_monitor/textual/zpoolpanel.py
zpool_monitor/zpool/__init__.py
zpool_monitor/zpool/formatting.py
zpool_monitor/zpool/scanstatus.py
zpool_monitor/zpool/vdev.py
zpool_monitor/zpool/vdevs.py
zpool_monitor/zpool/zpool.py
zpool_monitor-0.0.6.dist-info/licenses/LICENSE
zpool_monitor-0.0.6.dist-info/METADATA
zpool_monitor-0.0.6.dist-info/WHEEL
zpool_monitor-0.0.6.dist-info/entry_points.txt
zpool_monitor-0.0.6.dist-info/top_level.txt
zpool_monitor-0.0.6.dist-info/RECORD
