Metadata-Version: 2.4
Name: zpool-monitor
Version: 0.0.6
Summary: ZPool Status Monitor - A 'pretty' replacement for the 'zpool status' command
Author-email: Jason But <jbut@swin.edu.au>
License-Expression: MIT
Project-URL: Homepage, https://github.com/jason-but/zpool-monitor
Project-URL: Issues, https://github.com/jason-but/zpool-monitor/issues
Classifier: Programming Language :: Python :: 3
Classifier: Operating System :: OS Independent
Requires-Python: >=3.11
License-File: LICENSE
Requires-Dist: textual
Dynamic: license-file
